firehydrant_api_client/__init__.py
firehydrant_api_client/api_client.py
firehydrant_api_client/api_response.py
firehydrant_api_client/configuration.py
firehydrant_api_client/exceptions.py
firehydrant_api_client/py.typed
firehydrant_api_client/rest.py
firehydrant_api_client/api/__init__.py
firehydrant_api_client/api/ai_api.py
firehydrant_api_client/api/alerts_api.py
firehydrant_api_client/api/bootstrap_api.py
firehydrant_api_client/api/catalogs_api.py
firehydrant_api_client/api/change_types_api.py
firehydrant_api_client/api/changes_api.py
firehydrant_api_client/api/checklist_templates_api.py
firehydrant_api_client/api/conversations_api.py
firehydrant_api_client/api/current_user_api.py
firehydrant_api_client/api/custom_fields_api.py
firehydrant_api_client/api/entitlements_api.py
firehydrant_api_client/api/environments_api.py
firehydrant_api_client/api/form_configurations_api.py
firehydrant_api_client/api/functionalities_api.py
firehydrant_api_client/api/incident_roles_api.py
firehydrant_api_client/api/incident_tags_api.py
firehydrant_api_client/api/incident_types_api.py
firehydrant_api_client/api/incidents_api.py
firehydrant_api_client/api/infrastructures_api.py
firehydrant_api_client/api/integrations_api.py
firehydrant_api_client/api/lifecycles_api.py
firehydrant_api_client/api/metrics_api.py
firehydrant_api_client/api/noauth_api.py
firehydrant_api_client/api/nunc_api.py
firehydrant_api_client/api/nunc_connections_api.py
firehydrant_api_client/api/ping_api.py
firehydrant_api_client/api/post_mortems_api.py
firehydrant_api_client/api/priorities_api.py
firehydrant_api_client/api/processing_log_entries_api.py
firehydrant_api_client/api/reports_api.py
firehydrant_api_client/api/runbook_audits_api.py
firehydrant_api_client/api/runbooks_api.py
firehydrant_api_client/api/saved_searches_api.py
firehydrant_api_client/api/scheduled_maintenances_api.py
firehydrant_api_client/api/schedules_api.py
firehydrant_api_client/api/scim_api.py
firehydrant_api_client-1.0.18.dist-info/METADATA
firehydrant_api_client-1.0.18.dist-info/WHEEL
firehydrant_api_client-1.0.18.dist-info/top_level.txt
firehydrant_api_client-1.0.18.dist-info/RECORD
